vmngclient/__init__.py
vmngclient/api/__init__.py
vmngclient/api/admin_tech_api.py
vmngclient/api/administration.py
vmngclient/api/alarms_api.py
vmngclient/api/api_container.py
vmngclient/api/basic_api.py
vmngclient/api/config_device_inventory_api.py
vmngclient/api/config_group_api.py
vmngclient/api/configuration_groups/parcel.py
vmngclient/api/configuration_groups/parcels/aaa_parcel.py
vmngclient/api/configuration_groups/parcels/cellular_controller.py
vmngclient/api/dashboard_api.py
vmngclient/api/device_action_api.py
vmngclient/api/feature_profile_api.py
vmngclient/api/logs_api.py
vmngclient/api/monitoring_status_api.py
vmngclient/api/mtt_aaa_api.py
vmngclient/api/omp_api.py
vmngclient/api/packet_capture_api.py
vmngclient/api/parcel_api.py
vmngclient/api/partition_manager_api.py
vmngclient/api/policy_api.py
vmngclient/api/resource_pool_api.py
vmngclient/api/software_action_api.py
vmngclient/api/speedtest_api.py
vmngclient/api/task_status_api.py
vmngclient/api/template_api.py
vmngclient/api/templates/README.md
vmngclient/api/templates/cli_template.py
vmngclient/api/templates/device_template/device_template.py
vmngclient/api/templates/device_template/device_template_payload.json.j2
vmngclient/api/templates/device_variable.py
vmngclient/api/templates/feature_template.py
vmngclient/api/templates/feature_template_field.py
vmngclient/api/templates/feature_template_payload.py
vmngclient/api/templates/models/cisco_aaa_model.py
vmngclient/api/templates/models/cisco_banner_model.py
vmngclient/api/templates/models/cisco_bfd_model.py
vmngclient/api/templates/models/cisco_bgp_model.py
vmngclient/api/templates/models/cisco_logging_model.py
vmngclient/api/templates/models/cisco_ntp_model.py
vmngclient/api/templates/models/cisco_omp_model.py
vmngclient/api/templates/models/cisco_ospf.py
vmngclient/api/templates/models/cisco_ospfv3.py
vmngclient/api/templates/models/cisco_secure_internet_gateway.py
vmngclient/api/templates/models/cisco_snmp_model.py
vmngclient-0.22.1.dist-info/METADATA
vmngclient-0.22.1.dist-info/WHEEL
vmngclient-0.22.1.dist-info/RECORD
