Metadata-Version: 2.1
Name: vmngclient
Version: 0.22.1
Summary: vManage SDK for Python
Home-page: https://github.com/CiscoDevNet/vManage-client
Author: kagorski
Author-email: kagorski@cisco.com
Requires-Python: >=3.8.0,<4.0.0
Classifier: Programming Language :: Python :: 3
Classifier: Programming Language :: Python :: 3.8
Classifier: Programming Language :: Python :: 3.9
Classifier: Programming Language :: Python :: 3.10
Classifier: Programming Language :: Python :: 3.11
Requires-Dist: Jinja2 (>=3.1.2,<4.0.0)
Requires-Dist: attrs (>=21.4.0,<22.0.0)
Requires-Dist: ciscoconfparse (>=1.6.40,<2.0.0)
Requires-Dist: clint (>=0.5.1,<0.6.0)
Requires-Dist: flake8-quotes (>=3.3.1,<4.0.0)
Requires-Dist: packaging (>=23.0,<24.0)
Requires-Dist: pydantic (>=2.5,<3.0)
Requires-Dist: python-dateutil (>=2.8.2,<3.0.0)
Requires-Dist: requests (>=2.27.1,<3.0.0)
Requires-Dist: requests-toolbelt (>=1.0.0,<2.0.0)
Requires-Dist: tenacity (>=8.1.0,<9.0.0)
Project-URL: Repository, https://github.com/CiscoDevNet/vManage-client
